<?xml version="1.0" encoding="UTF-8"?>
<!DOCTYPE tv SYSTEM "xmltv.dtd">

<tv source-info-url="http://allfrtv.com/" source-info-name="XML TV Fr" generator-info-name="XML TV Fr" generator-info-url="http://allfrtv.com/">
  <channel id="lcn/LCN">
    <display-name>LCN</display-name>
    <icon src="" />
  </channel>
<channel id="CanalSavoir">
    <display-name>CanalSavoir</display-name>
    <icon src="" />
  </channel>
<channel id="TVASports">
    <display-name>TVASports</display-name>
    <icon src="" />
  </channel>
<channel id="TVASports2">
    <display-name>TVASports2</display-name>
    <icon src="" />
  </channel>
<channel id="ICIARTV">
    <display-name>ICIARTV</display-name>
    <icon src="" />
  </channel>
<channel id="Casa">
    <display-name>Casa</display-name>
    <icon src="" />
  </channel>
<channel id="ADDIKTV">
    <display-name>ADDIKTV</display-name>
    <icon src="" />
  </channel>
<channel id="CanalD">
    <display-name>CanalD</display-name>
    <icon src="" />
  </channel>
<channel id="Vrak">
    <display-name>Vrak</display-name>
    <icon src="" />
  </channel>
<channel id="MoiEtCie">
    <display-name>MoiEtCie</display-name>
    <icon src="" />
  </channel>
<channel id="TFO">
    <display-name>TFO</display-name>
    <icon src="" />
  </channel>
<channel id="TeleMagino">
    <display-name>TeleMagino</display-name>
    <icon src="" />
  </channel>
<channel id="FamilyJr">
    <display-name>FamilyJr</display-name>
    <icon src="" />
  </channel>
<channel id="CinePop">
    <display-name>CinePop</display-name>
    <icon src="" />
  </channel>
<channel id="FrissonsTV">
    <display-name>FrissonsTV</display-name>
    <icon src="" />
  </channel>
<channel id="RDS">
    <display-name>RDS</display-name>
    <icon src="" />
  </channel>
<channel id="RDS2">
    <display-name>RDS2</display-name>
    <icon src="" />
  </channel>
<channel id="RDSInfo">
    <display-name>RDSInfo</display-name>
    <icon src="" />
  </channel>
<channel id="SeriesPlus">
    <display-name>SeriesPlus</display-name>
    <icon src="" />
  </channel>
<channel id="HistoriaCA">
    <display-name>HistoriaCA</display-name>
    <icon src="" />
  </channel>
<channel id="ZTele">
    <display-name>ZTele</display-name>
    <icon src="" />
  </channel>
<channel id="PlanetePlusCA">
    <display-name>PlanetePlusCA</display-name>
    <icon src="" />
  </channel>
<channel id="ICIExplora">
    <display-name>ICIExplora</display-name>
    <icon src="" />
  </channel>
<channel id="prise2">
    <display-name>prise2</display-name>
    <icon src="" />
  </channel>
<channel id="Yoopa">
    <display-name>Yoopa</display-name>
    <icon src="" />
  </channel>
<channel id="TeletoonCA">
    <display-name>TeletoonCA</display-name>
    <icon src="" />
  </channel>
<channel id="DisneyChannelCA">
    <display-name>DisneyChannelCA</display-name>
    <icon src="" />
  </channel>
<channel id="SuperEcran1">
    <display-name>SuperEcran1</display-name>
    <icon src="" />
  </channel>
<channel id="SuperEcran2">
    <display-name>SuperEcran2</display-name>
    <icon src="" />
  </channel>
<channel id="SuperEcran3">
    <display-name>SuperEcran3</display-name>
    <icon src="" />
  </channel>
<channel id="SuperEcran4">
    <display-name>SuperEcran4</display-name>
    <icon src="" />
  </channel>
<channel id="TeleQuebec">
    <display-name>TeleQuebec</display-name>
    <icon src="" />
  </channel>
<channel id="MATV">
    <display-name>MATV</display-name>
    <icon src="" />
  </channel>
<channel id="Investigation">
    <display-name>Investigation</display-name>
    <icon src="" />
  </channel>
<channel id="CanalPlusInternat">
    <display-name>CanalPlusInternat</display-name>
    <icon src="" />
  </channel>
<channel id="Unis">
    <display-name>Unis</display-name>
    <icon src="" />
  </channel>
<channel id="Evasion">
    <display-name>Evasion</display-name>
    <icon src="" />
  </channel>
<channel id="CanalVie">
    <display-name>CanalVie</display-name>
    <icon src="" />
  </channel>
<channel id="Zeste">
    <display-name>Zeste</display-name>
    <icon src="" />
  </channel>
<channel id="Saisons">
    <display-name>Saisons</display-name>
    <icon src="" />
  </channel>
<channel id="RFO">
    <display-name>RFO</display-name>
    <icon src="" />
  </channel>
</tv>